msfvenomgui/__init__.py
msfvenomgui/command_builder.py
msfvenomgui/gui.py
msfvenomgui/main.py
msfvenomgui-0.2.3.dist-info/LICENSE
msfvenomgui-0.2.3.dist-info/METADATA
msfvenomgui-0.2.3.dist-info/WHEEL
msfvenomgui-0.2.3.dist-info/entry_points.txt
msfvenomgui-0.2.3.dist-info/RECORD
