Metadata-Version: 2.1
Name: msfvenomgui
Version: 0.2.3
Summary: msfvenomgui provides a graphical UI over Metasploit's msfvenom tool.
License: GPL-3.0-only
Author: bluesentinelsec
Author-email: bluesentinel@protonmail.com
Requires-Python: >=3.9,<4.0
Classifier: License :: OSI Approved :: GNU General Public License v3 (GPLv3)
Classifier: Programming Language :: Python :: 3
Classifier: Programming Language :: Python :: 3.9
Classifier: Programming Language :: Python :: 3.10
Classifier: Programming Language :: Python :: 3.11
Requires-Dist: pytest (>=7.3.1,<8.0.0)
